pyspelling/__init__.py
pyspelling/__main__.py
pyspelling/__meta__.py
pyspelling/plugin.py
pyspelling/filters/__init__.py
pyspelling/filters/context.py
pyspelling/filters/cpp.py
pyspelling/filters/html.py
pyspelling/filters/javascript.py
pyspelling/filters/markdown.py
pyspelling/filters/odf.py
pyspelling/filters/ooxml.py
pyspelling/filters/python.py
pyspelling/filters/stylesheets.py
pyspelling/filters/text.py
pyspelling/filters/url.py
pyspelling/filters/xml.py
pyspelling/flow_control/__init__.py
pyspelling/flow_control/wildcard.py
pyspelling/util/__init__.py
pyspelling-2.11.dist-info/METADATA
pyspelling-2.11.dist-info/WHEEL
pyspelling-2.11.dist-info/entry_points.txt
pyspelling-2.11.dist-info/licenses/LICENSE.md
pyspelling-2.11.dist-info/RECORD
