Metadata-Version: 2.4
Name: pyspelling
Version: 2.11
Summary: Spell checker.
Project-URL: Homepage, https://github.com/facelessuser/pyspelling
Author-email: Isaac Muse <Isaac.Muse@gmail.com>
License-Expression: MIT
License-File: LICENSE.md
Keywords: spelling
Classifier: Development Status :: 5 - Production/Stable
Classifier: Environment :: Console
Classifier: Intended Audience :: Developers
Classifier: License :: OSI Approved :: MIT License
Classifier: Operating System :: OS Independent
Classifier: Programming Language :: Python :: 3
Classifier: Programming Language :: Python :: 3.9
Classifier: Programming Language :: Python :: 3.10
Classifier: Programming Language :: Python :: 3.11
Classifier: Programming Language :: Python :: 3.12
Classifier: Programming Language :: Python :: 3.13
Classifier: Programming Language :: Python :: 3.14
Classifier: Topic :: Internet :: WWW/HTTP :: Dynamic Content
Classifier: Topic :: Software Development :: Libraries :: Python Modules
Requires-Python: >=3.9
Requires-Dist: beautifulsoup4
Requires-Dist: html5lib
Requires-Dist: lxml
Requires-Dist: markdown
Requires-Dist: pyyaml
Requires-Dist: soupsieve>=1.8
Requires-Dist: wcmatch>=8.5
